baler_operator/__init__.py
baler_operator/app.py
baler_operator/assets/annotations_schema.json
baler_operator/assets/configmap.yaml
baler_operator/assets/deployment.yaml
baler_operator/assets/haystack_supported_versions.txt
baler_operator/assets/pipeline_schema.json
baler_operator/assets/service.yaml
baler_operator/assets/documentstores/ElasticsearchDocumentStore/deployment.yaml
baler_operator/assets/documentstores/ElasticsearchDocumentStore/service.yaml
baler_operator/config/__init__.py
baler_operator/config/core.py
baler_operator/documentstore/__init__.py
baler_operator/documentstore/core.py
baler_operator/errors/__init__.py
baler_operator/errors/core.py
baler_operator/kube/__init__.py
baler_operator/kube/core.py
baler_operator/pipelines/__init__.py
baler_operator/pipelines/core.py
baler_operator/utils/__init__.py
baler_operator/utils/core.py
baler_operator-0.8.3.dist-info/METADATA
baler_operator-0.8.3.dist-info/WHEEL
baler_operator-0.8.3.dist-info/licenses/LICENSE.md
baler_operator-0.8.3.dist-info/RECORD
