Metadata-Version: 2.3
Name: baler-operator
Version: 0.8.3
Summary: A Kubernetes operator for managing NLP framework deplotments.
Author-email: Greg Nagy <greg@gatecastle.com>
License: 
License-File: LICENSE.md
Keywords: baler,baler-operator,haystack,kubernetes,nlp,operator
Classifier: License :: OSI Approved :: Apache Software License
Classifier: Operating System :: OS Independent
Classifier: Programming Language :: Python :: 3
Requires-Python: >=3.8
Requires-Dist: jinja2==3.1.3
Requires-Dist: jsonschema==4.21.1
Requires-Dist: kopf==1.37.1
Requires-Dist: kubernetes==29.0.0
Provides-Extra: dev
Requires-Dist: myst-parser; extra == 'dev'
Requires-Dist: sphinx-rtd-theme; extra == 'dev'
Requires-Dist: sphinx==4.4.0; extra == 'dev'
